MANIFEST.in
setup.cfg
setup.py
Deliverance.Rewrite.egg-info/PKG-INFO
Deliverance.Rewrite.egg-info/SOURCES.txt
Deliverance.Rewrite.egg-info/dependency_links.txt
Deliverance.Rewrite.egg-info/entry_points.txt
Deliverance.Rewrite.egg-info/not-zip-safe
Deliverance.Rewrite.egg-info/requires.txt
Deliverance.Rewrite.egg-info/top_level.txt
deliverance/__init__.py
deliverance/exceptions.py
deliverance/garbagecollect.py
deliverance/log.py
deliverance/middleware.py
deliverance/monkeys.py
deliverance/pagematch.py
deliverance/paster_templates.py
deliverance/proxy.py
deliverance/proxycommand.py
deliverance/pyref.py
deliverance/rules.py
deliverance/ruleset.py
deliverance/security.py
deliverance/selector.py
deliverance/stringmatch.py
deliverance/themeref.py
deliverance/editor/__init__.py
deliverance/editor/editor_template.html
deliverance/editor/editorapp.py
deliverance/editor/view_dir_template.html
deliverance/editor/media/delivxml.js
deliverance/editor/media/style.css
deliverance/editor/media/editarea/change_log.txt
deliverance/editor/media/editarea/license_apache.txt
deliverance/editor/media/editarea/license_lgpl.txt
deliverance/editor/media/editarea/todo.txt
deliverance/editor/media/editarea/edit_area/autocompletion.js
deliverance/editor/media/editarea/edit_area/edit_area.css
deliverance/editor/media/editarea/edit_area/edit_area.js
deliverance/editor/media/editarea/edit_area/edit_area_compressor.php
deliverance/editor/media/editarea/edit_area/edit_area_full.gz
deliverance/editor/media/editarea/edit_area/edit_area_full.js
deliverance/editor/media/editarea/edit_area/edit_area_full_with_plugins.gz
deliverance/editor/media/editarea/edit_area/edit_area_full_with_plugins.js
deliverance/editor/media/editarea/edit_area/edit_area_functions.js
deliverance/editor/media/editarea/edit_area/edit_area_loader.js
deliverance/editor/media/editarea/edit_area/elements_functions.js
deliverance/editor/media/editarea/edit_area/highlight.js
deliverance/editor/media/editarea/edit_area/keyboard.js
deliverance/editor/media/editarea/edit_area/license.txt
deliverance/editor/media/editarea/edit_area/manage_area.js
deliverance/editor/media/editarea/edit_area/reg_syntax.js
deliverance/editor/media/editarea/edit_area/regexp.js
deliverance/editor/media/editarea/edit_area/resize_area.js
